{
  "kind": "bugfix-verify-green",
  "bug": "bump-poll-duplicate-pr",
  "sha": "c29f24a35e3e85f8f83a24edd55fc6a7b4dda33e",
  "treeSha": "24d9912c4dfd4c5c2737887641a4979cc567f3c2",
  "regression": {
    "exit": 0,
    "passed": true,
    "outputTail": "autoDeploy PR keeps its arming)\nok 96 bump-poll never calls gh pr create directly (PR creation goes through ensure-bump-pr)\nok 97 bump-poll never pushes the bump branch directly (a skip decision must mutate nothing)\nok 98 bump-poll drives the PR step through tools/ensure-bump-pr.ts\nok 99 the bump branch name carries no RUN_ID (same bump converges to one branch)\nok 100 the bump step creates the branch, bumps the tag, commits, and only then calls ensure-bump-pr (in that order)\nok 101 auto-merge is armed only by ensure-bump-pr (bump-poll never runs the shared script itself)\nok 102 the lane is forwarded verbatim from the planner (only autoDeploy can arm auto-merge)\nok 103 the two lanes reach the executor with their own --action (hermetic run of the real bump step)\nok 104 the pr-sweeper no longer selects bump-poll branches (the executor owns that namespace)\nok 105 no workflow advances a bump-poll PR (gh pr update-branch and gh pr merge never see that namespace)\nok 106 the reconcile pass runs with NO planner output at all (no plan.json, no reader token) — its subjects come from the namespace\nok 107 the reconcile job carries no reader token and no planner step (revocation cannot be starved by candidate planning)\nok 108 one app's half-written worktree never leaks into the next item's commit, and never starves it (real git isolation, run still red)\nok 109 the real-git isolation witness has teeth (removing 'git checkout -f main' lets page's staged residue leak into trip-mate's commit)\nok 110 a failing reconcile job never starves the bump loop, and a failing bump loop never starves revocation (and both still turn the run red)\nok 111 a missing reader skips ONLY the poll job — revocation runs on writer credentials alone (both job gates evaluated for real)\nok 112 the commit the workflow EFFECTIVELY makes carries the identity and message the executor proves ownership with\nok 113 the effective-ownership witness has teeth (a later git config override and a --amend both flip it RED)\n"
  },
  "characterization": {
    "exit": 0,
    "green": true,
    "outputTail": "7 bespoke descriptor without autoDeploy is fail-closed (propose-pr, never auto bump)\nok 38 bump rewrites only image.tag in the app's values.yaml\nok 39 bump is idempotent (second run is a no-op)\nok 40 bump --digest records image.digest alongside the tag\nok 41 bump rejects a malformed digest with exit 2\nok 42 bump with same tag and digest is a no-op\nok 43 tag-only bump removes a stale digest (image must follow the new tag)\nok 44 bump refuses path traversal outside apps/\nok 45 bump workflow joins the global homelab-mutation queue (no pending loss)\nok 46 bump rejects an unknown flag with exit 2 (typo'd --digest must not silently drop the pin)\nok 47 bump --expect-current aborts when current tag differs (races-4 TOCTOU)\nok 48 bump --expect-current proceeds when current tag matches\nok 49 bump rejects a value-flag with no value (arity, F2 digest-pin downgrade class)\nok 50 bump rejects a value-flag whose value is another --flag (arity)\nok 51 bump: v1 repository_dispatch path fully removed (writeback-dispatch gone)\nok 52 bump --pin edits the inline repo:tag@digest scalar in a bespoke deployment.yaml\nok 53 bump --pin without --digest is refused (bespoke pins are always digest-pinned)\nok 54 bump --pin --expect-current aborts on a tag mismatch (TOCTOU, exit 3)\nok 55 bump --pin is idempotent (same tag+digest is a no-op)\nok 56 bump --pin refuses a descriptor outside platform/ (path traversal guard)\nok 57 bump also refreshes the digest-exporter APPS tag for an app already listed\nok 58 bump leaves the digest-exporter byte-identical for an app not listed in APPS\nok 59 bump-poll passes --expect-current to bump-tag after checkout main (TOCTOU guard)\nok 60 bump-poll still checks out main fresh before each branch (snapshot reset)\nok 61 expect-current is sourced from the planner snapshot, not re-read from live values.yaml (F2)\nok 62 bump-poll branches on the bespoke pin descriptor and passes --pin to bump-tag\nok 63 bump-poll git-adds the planner writePath (unifies apps and bespoke lanes)\n"
  },
  "repro": null,
  "note": "written by bugfix-status.mjs --verify-flip (script-owned re-execution)"
}
